jupyterlab_rainbow_brackets/__init__.py
jupyterlab_rainbow_brackets/_version.py
jupyterlab_rainbow_brackets-0.1.0.data/data/share/jupyter/labextensions/jupyterlab-rainbow-brackets/package.json
jupyterlab_rainbow_brackets-0.1.0.data/data/share/jupyter/labextensions/jupyterlab-rainbow-brackets/schemas/jupyterlab-rainbow-brackets/package.json.orig
jupyterlab_rainbow_brackets-0.1.0.data/data/share/jupyter/labextensions/jupyterlab-rainbow-brackets/schemas/jupyterlab-rainbow-brackets/plugin.json
jupyterlab_rainbow_brackets-0.1.0.data/data/share/jupyter/labextensions/jupyterlab-rainbow-brackets/static/36.d5fa9717a5178960c22f.js
jupyterlab_rainbow_brackets-0.1.0.data/data/share/jupyter/labextensions/jupyterlab-rainbow-brackets/static/509.698dcd104632e9ffbb70.js
jupyterlab_rainbow_brackets-0.1.0.data/data/share/jupyter/labextensions/jupyterlab-rainbow-brackets/static/655.eeab2018a1ccaa1b1756.js
jupyterlab_rainbow_brackets-0.1.0.data/data/share/jupyter/labextensions/jupyterlab-rainbow-brackets/static/728.7ca7a77fa0fd042976e6.js
jupyterlab_rainbow_brackets-0.1.0.data/data/share/jupyter/labextensions/jupyterlab-rainbow-brackets/static/remoteEntry.3aa78e2892a56fe0b397.js
jupyterlab_rainbow_brackets-0.1.0.data/data/share/jupyter/labextensions/jupyterlab-rainbow-brackets/static/style.js
jupyterlab_rainbow_brackets-0.1.0.data/data/share/jupyter/labextensions/jupyterlab-rainbow-brackets/static/third-party-licenses.json
jupyterlab_rainbow_brackets-0.1.0.data/data/share/jupyter/labextensions/jupyterlab-rainbow-brackets/install.json
jupyterlab_rainbow_brackets-0.1.0.dist-info/METADATA
jupyterlab_rainbow_brackets-0.1.0.dist-info/WHEEL
jupyterlab_rainbow_brackets-0.1.0.dist-info/licenses/LICENSE
jupyterlab_rainbow_brackets-0.1.0.dist-info/RECORD
