Metadata-Version: 2.3
Name: jupyterlab-rainbow-brackets
Version: 0.1.0
Summary: A JupyterLab extension adding rainbow brackets/parentheses to the editor.
Project-URL: Homepage, https://github.com/krassowski/jupyterlab-rainbow-brackets
Project-URL: Bug Tracker, https://github.com/krassowski/jupyterlab-rainbow-brackets/issues
Project-URL: Repository, https://github.com/krassowski/jupyterlab-rainbow-brackets.git
Author: Michał Krassowski
License: BSD 3-Clause License
License-File: LICENSE
Classifier: Framework :: Jupyter
Classifier: Framework :: Jupyter :: JupyterLab
Classifier: Framework :: Jupyter :: JupyterLab :: 4
Classifier: Framework :: Jupyter :: JupyterLab :: Extensions
Classifier: Framework :: Jupyter :: JupyterLab :: Extensions :: Prebuilt
Classifier: License :: OSI Approved :: BSD License
Classifier: Programming Language :: Python
Classifier: Programming Language :: Python :: 3
Classifier: Programming Language :: Python :: 3.8
Classifier: Programming Language :: Python :: 3.9
Classifier: Programming Language :: Python :: 3.10
Classifier: Programming Language :: Python :: 3.11
Classifier: Programming Language :: Python :: 3.12
Requires-Python: >=3.8
